[{"id":1,"product":"Wine - Lou Black Shiraz","price":"£0.56","department":"Baby"},
{"id":2,"product":"Butter Sweet","price":"£2.30","department":"Books"},
{"id":3,"product":"Crab - Back Fin Meat, Canned","price":"£7.93","department":"Industrial"},
{"id":4,"product":"Chinese Foods - Pepper Beef","price":"£5.29","department":"Grocery"},
{"id":5,"product":"Beer - Maudite","price":"£2.07","department":"Clothing"},
{"id":6,"product":"Foil Cont Round","price":"£4.34","department":"Electronics"},
{"id":7,"product":"Wiberg Cure","price":"£2.07","department":"Baby"},
{"id":8,"product":"Muffin Mix - Morning Glory","price":"£8.75","department":"Jewelery"},
{"id":9,"product":"Shrimp - Baby, Cold Water","price":"£6.08","department":"Music"},
{"id":10,"product":"Tuna - Salad Premix","price":"£8.78","department":"Baby"},
{"id":11,"product":"Ecolab - Medallion","price":"£0.84","department":"Sports"},
{"id":12,"product":"Dooleys Toffee","price":"£9.30","department":"Movies"},
{"id":13,"product":"Vinegar - Balsamic","price":"£7.80","department":"Grocery"},
{"id":14,"product":"Veal - Insides, Grains","price":"£8.23","department":"Sports"},
{"id":15,"product":"Table Cloth 81x81 Colour","price":"£3.63","department":"Jewelery"},
{"id":16,"product":"Bread - Burger","price":"£6.94","department":"Shoes"},
{"id":17,"product":"Broom Handle","price":"£7.79","department":"Baby"},
{"id":18,"product":"Sauce - Rosee","price":"£1.27","department":"Grocery"},
{"id":19,"product":"Yogurt - Raspberry, 175 Gr","price":"£0.14","department":"Garden"},
{"id":20,"product":"Roe - Flying Fish","price":"£2.82","department":"Music"},
{"id":21,"product":"Squid - U - 10 Thailand","price":"£8.06","department":"Kids"},
{"id":22,"product":"Cheese - Mozzarella","price":"£8.55","department":"Baby"},
{"id":23,"product":"Puree - Strawberry","price":"£3.62","department":"Baby"},
{"id":24,"product":"Table Cloth - 53x69 Colour","price":"£2.69","department":"Automotive"},
{"id":25,"product":"Yogurt - Blueberry, 175 Gr","price":"£1.83","department":"Electronics"},
{"id":26,"product":"Bread - Focaccia Quarter","price":"£4.62","department":"Grocery"},
{"id":27,"product":"Beans - Kidney, Canned","price":"£2.36","department":"Tools"},
{"id":28,"product":"Bread - Onion Focaccia","price":"£4.45","department":"Toys"},
{"id":29,"product":"Lettuce - Radicchio","price":"£5.75","department":"Beauty"},
{"id":30,"product":"Tortillas - Flour, 10","price":"£6.63","department":"Movies"},
{"id":31,"product":"Goldschalger","price":"£5.20","department":"Tools"},
{"id":32,"product":"Bread Fig And Almond","price":"£7.64","department":"Beauty"},
{"id":33,"product":"Hold Up Tool Storage Rack","price":"£3.64","department":"Tools"},
{"id":34,"product":"Lettuce - Romaine","price":"£8.84","department":"Computers"},
{"id":35,"product":"Wine - German Riesling","price":"£6.07","department":"Clothing"},
{"id":36,"product":"Lemon Grass","price":"£8.27","department":"Kids"},
{"id":37,"product":"Relish","price":"£9.92","department":"Computers"},
{"id":38,"product":"Tomato - Tricolor Cherry","price":"£1.69","department":"Tools"},
{"id":39,"product":"Jam - Apricot","price":"£1.14","department":"Toys"},
{"id":40,"product":"Wine - Chablis 2003 Champs","price":"£5.73","department":"Electronics"},
{"id":41,"product":"Rice - Sushi","price":"£8.08","department":"Grocery"},
{"id":42,"product":"Calypso - Strawberry Lemonade","price":"£1.42","department":"Health"},
{"id":43,"product":"Zucchini - Yellow","price":"£1.35","department":"Industrial"},
{"id":44,"product":"Longos - Chicken Caeser Salad","price":"£8.72","department":"Automotive"},
{"id":45,"product":"Pepperoni Slices","price":"£1.45","department":"Grocery"},
{"id":46,"product":"Sultanas","price":"£6.63","department":"Computers"},
{"id":47,"product":"Lamb - Sausage Casings","price":"£4.89","department":"Tools"},
{"id":48,"product":"Silicone Parch. 16.3x24.3","price":"£1.14","department":"Movies"},
{"id":49,"product":"Quinoa","price":"£7.04","department":"Health"},
{"id":50,"product":"Wine - Pinot Noir Pond Haddock","price":"£2.81","department":"Sports"},
{"id":51,"product":"Cheese - Cheddar With Claret","price":"£8.94","department":"Clothing"},
{"id":52,"product":"Burger Veggie","price":"£0.01","department":"Shoes"},
{"id":53,"product":"Oil - Shortening,liqud, Fry","price":"£3.00","department":"Electronics"},
{"id":54,"product":"Chocolate - Semi Sweet","price":"£6.92","department":"Kids"},
{"id":55,"product":"Nut - Hazelnut, Whole","price":"£6.42","department":"Beauty"},
{"id":56,"product":"Pie Box - Cello Window 2.5","price":"£0.04","department":"Outdoors"},
{"id":57,"product":"Soup Bowl Clear 8oz92008","price":"£8.95","department":"Outdoors"},
{"id":58,"product":"Garlic - Primerba, Paste","price":"£0.73","department":"Sports"},
{"id":59,"product":"Sobe - Green Tea","price":"£7.95","department":"Outdoors"},
{"id":60,"product":"Versatainer Nc - 888","price":"£0.43","department":"Industrial"},
{"id":61,"product":"Flour Pastry Super Fine","price":"£8.92","department":"Toys"},
{"id":62,"product":"Squeeze Bottle","price":"£1.13","department":"Outdoors"},
{"id":63,"product":"Dr. Pepper - 355ml","price":"£4.08","department":"Beauty"},
{"id":64,"product":"Appetizer - Southwestern","price":"£8.10","department":"Clothing"},
{"id":65,"product":"Ice Cream Bar - Rolo Cone","price":"£1.08","department":"Baby"},
{"id":66,"product":"Muffin Mix - Raisin Bran","price":"£3.51","department":"Music"},
{"id":67,"product":"Pork - Tenderloin, Frozen","price":"£2.69","department":"Kids"},
{"id":68,"product":"Napkin White - Starched","price":"£9.62","department":"Home"},
{"id":69,"product":"Milk - Condensed","price":"£7.59","department":"Electronics"},
{"id":70,"product":"Asparagus - Green, Fresh","price":"£9.33","department":"Baby"},
{"id":71,"product":"Cheese - Wine","price":"£8.52","department":"Electronics"},
{"id":72,"product":"Tofu - Soft","price":"£5.64","department":"Shoes"},
{"id":73,"product":"Pork - Side Ribs","price":"£5.78","department":"Games"},
{"id":74,"product":"Creme De Menth - White","price":"£2.31","department":"Sports"},
{"id":75,"product":"Anchovy Fillets","price":"£6.92","department":"Beauty"},
{"id":76,"product":"Veal - Osso Bucco","price":"£6.94","department":"Sports"},
{"id":77,"product":"Coffee Decaf Colombian","price":"£5.73","department":"Beauty"},
{"id":78,"product":"Puree - Raspberry","price":"£2.85","department":"Games"},
{"id":79,"product":"Wine - Tio Pepe Sherry Fino","price":"£5.78","department":"Sports"},
{"id":80,"product":"Wine - Cotes Du Rhone","price":"£7.20","department":"Home"},
{"id":81,"product":"Oil - Pumpkinseed","price":"£0.03","department":"Grocery"},
{"id":82,"product":"Butter - Salted","price":"£6.47","department":"Clothing"},
{"id":83,"product":"Nantucket - Orange Mango Cktl","price":"£5.83","department":"Health"},
{"id":84,"product":"Soup - Campbells - Tomato","price":"£5.27","department":"Toys"},
{"id":85,"product":"Yogurt - Blueberry, 175 Gr","price":"£8.47","department":"Garden"},
{"id":86,"product":"Garlic Powder","price":"£6.75","department":"Grocery"},
{"id":87,"product":"Quail - Whole, Boneless","price":"£6.99","department":"Industrial"},
{"id":88,"product":"Jam - Raspberry,jar","price":"£8.20","department":"Industrial"},
{"id":89,"product":"Liqueur - Melon","price":"£5.32","department":"Tools"},
{"id":90,"product":"Appetizer - Seafood Assortment","price":"£4.53","department":"Industrial"},
{"id":91,"product":"Soup - Campbells Bean Medley","price":"£7.63","department":"Jewelery"},
{"id":92,"product":"Sausage - Chorizo","price":"£8.30","department":"Sports"},
{"id":93,"product":"Cookie - Dough Variety","price":"£6.95","department":"Tools"},
{"id":94,"product":"Chips - Doritos","price":"£4.30","department":"Kids"},
{"id":95,"product":"Wine - Red, Cabernet Merlot","price":"£1.85","department":"Kids"},
{"id":96,"product":"Soup - Clam Chowder, Dry Mix","price":"£3.02","department":"Jewelery"},
{"id":97,"product":"Slt - Individual Portions","price":"£7.76","department":"Toys"},
{"id":98,"product":"Wine - Chenin Blanc K.w.v.","price":"£3.16","department":"Grocery"},
{"id":99,"product":"Snapple Raspberry Tea","price":"£1.84","department":"Clothing"},
{"id":100,"product":"Sugar - Palm","price":"£4.83","department":"Garden"}]